Metadata-Version: 2.1
Name: mailing-logs
Version: 0.2
Summary: Easy logs mailing
Home-page: https://github.com/cicwak/mailing-logs
Download-URL: https://github.com/cicwak/mailing-logs/archive/refs/tags/0.2.tar.gz
Author: Konstantin Ponomarev(cicwak)
Author-email: cicwak@gmail.com
License: MIT
Keywords: MAILING,LOGS,BEST
Classifier: Programming Language :: Python :: 3
Classifier: Programming Language :: Python :: 3.4
Classifier: Programming Language :: Python :: 3.5
Classifier: Programming Language :: Python :: 3.6
Classifier: Programming Language :: Python :: 3.7
Classifier: Programming Language :: Python :: 3.8
Classifier: Programming Language :: Python :: 3.9
Classifier: Programming Language :: Python :: 3.10
Classifier: Programming Language :: Python :: 3.11
Classifier: Programming Language :: Python :: 3.12
License-File: LICENSE.txt
Requires-Dist: requests
